{
    "dollar": "usd",
    "dollars": "usd",
    "usdollar": "usd",
    "us": "usd",
    "usd": "usd",
    "american": "usd",
    "buck": "usd",
    "bucks": "usd",
    "greenback": "usd",
    "greenbacks": "usd",
    "greens": "usd",
    "usa": "usd",
    "america": "usd",
    "unitedstates": "usd",
    "stateside": "usd",
    "dc": "usd",
    "george": "usd",
    "benjamins": "usd",
    "benji": "usd",
    "deadpresidents": "usd",
    "jackson": "usd",
    "hamilton": "usd",
    "washington": "usd",
    "bones": "usd",
    "clams": "usd",
    "dough": "usd",
    "singles": "usd",
    "frogskin": "usd",
    "simoleons": "usd",
    "euro": "eur",
    "uro": "eur",
    "euros": "eur",
    "eur": "eur",
    "european": "eur",
    "eu": "eur",
    "eurozone": "eur",
    "€": "eur",
    "ecb": "eur",
    "commoncurrency": "eur",
    "eurodollar": "eur",
    "fiber": "eur",
    "singlecurrency": "eur",
    "teuro": "eur",
    "yen": "jpy",
    "jpy": "jpy",
    "japanese": "jpy",
    "japan": "jpy",
    "nippon": "jpy",
    "nihon": "jpy",
    "en": "jpy",
    "¥": "jpy",
    "円": "jpy",
    "pound": "gbp",
    "pounds": "gbp",
    "sterling": "gbp",
    "gbp": "gbp",
    "british": "gbp",
    "quid": "gbp",
    "ukp": "gbp",
    "uk": "gbp",
    "unitedkingdom": "gbp",
    "greatbritain": "gbp",
    "poundsterling": "gbp",
    "stg": "gbp",
    "nicker": "gbp",
    "cable": "gbp",
    "pony": "gbp",
    "fiver": "gbp",
    "tenner": "gbp",
    "score": "gbp",
    "monkey": "gbp",
    "ton": "gbp",
    "grand": "gbp",
    "£": "gbp",
    "scotland": "gbp",
    "wales": "gbp",
    "nireland": "gbp",
    "northernireland": "gbp",
    "london": "gbp",
    "english": "gbp",
    "scotish": "gbp",
    "welsh": "gbp",
    "rupee": "inr",
    "rupees": "inr",
    "inr": "inr",
    "indian": "inr",
    "india": "inr",
    "rs": "inr",
    "rupiya": "inr",
    "rupaye": "inr",
    "rupaiya": "inr",
    "bharat": "inr",
    "hindustan": "inr",
    "₹": "inr",
    "रुपया": "inr",
    "रुपये": "inr",
    "रु": "inr",
    "paisa": "inr",
    "bombay": "inr",
    "delhi": "inr",
    "mumbai": "inr",
    "chennai": "inr",
    "bengaluru": "inr",
    "bangalore": "inr",
    "yuan": "cny",
    "rmb": "cny",
    "cny": "cny",
    "renminbi": "cny",
    "chinese": "cny",
    "kuai": "cny",
    "china": "cny",
    "redback": "cny",
    "offshoreyuan": "cny",
    "onshoreyuan": "cny",
    "cnh": "cny",
    "元": "cny",
    "人民币": "cny",
    "beijing": "cny",
    "shanghai": "cny",
    "shenzhen": "cny",
    "mainlander": "cny",
    "prc": "cny",
    "won": "krw",
    "krw": "krw",
    "korean": "krw",
    "korea": "krw",
    "southkorean": "krw",
    "southkorea": "krw",
    "skorea": "krw",
    "seoul": "krw",
    "busan": "krw",
    "원": "krw",
    "한국": "krw",
    "대한민국": "krw",
    "hanguk": "krw",
    "daehan": "krw",
    "cad": "cad",
    "canadian": "cad",
    "canada": "cad",
    "loonie": "cad",
    "loonies": "cad",
    "canuck": "cad",
    "c$": "cad",
    "cdn": "cad",
    "cdndollar": "cad",
    "toonie": "cad",
    "maple": "cad",
    "beaver": "cad",
    "northernpeso": "cad",
    "ontario": "cad",
    "quebec": "cad",
    "toronto": "cad",
    "vancouver": "cad",
    "montreal": "cad",
    "ottawa": "cad",
    "aud": "aud",
    "aussie": "aud",
    "australian": "aud",
    "australia": "aud",
    "ozzie": "aud",
    "oz": "aud",
    "dollarydoos": "aud",
    "a$": "aud",
    "downunder": "aud",
    "roo": "aud",
    "sydney": "aud",
    "melbourne": "aud",
    "brisbane": "aud",
    "perth": "aud",
    "goldback": "aud",
    "aussiedollar": "aud",
    "oceania": "aud",
    "franc": "chf",
    "francs": "chf",
    "chf": "chf",
    "swiss": "chf",
    "switzerland": "chf",
    "swissy": "chf",
    "suisse": "chf",
    "schweiz": "chf",
    "schweizerfranken": "chf",
    "confoederatiohelvetica": "chf",
    "helvetica": "chf",
    "fr": "chf",
    "sfr": "chf",
    "geneva": "chf",
    "zurich": "chf",
    "bern": "chf",
    "alps": "chf",
    "alpine": "chf",
    "ruble": "rub",
    "rubles": "rub",
    "rub": "rub",
    "russian": "rub",
    "russia": "rub",
    "rouble": "rub",
    "roubles": "rub",
    "москва": "rub",
    "рубль": "rub",
    "рубли": "rub",
    "руб": "rub",
    "₽": "rub",
    "moscow": "rub",
    "stpetersburg": "rub",
    "siberian": "rub",
    "rossiya": "rub",
    "bitcoin": "btc",
    "btc": "btc",
    "xbt": "btc",
    "bitcoins": "btc",
    "satoshi": "btc",
    "sats": "btc",
    "digitalgold": "btc",
    "satoshis": "btc",
    "coin": "btc",
    "₿": "btc",
    "btcoin": "btc",
    "coinbase": "btc",
    "cryptogold": "btc",
    "nakamoto": "btc",
    "bitc": "btc",
    "hodl": "btc",
    "orangecoin": "btc",
    "magicinternetmoney": "btc",
    "corn": "btc",
    "kingcrypto": "btc",
    "ethereum": "eth",
    "ether": "eth",
    "eth": "eth",
    "gwei": "eth",
    "wei": "eth",
    "vitalik": "eth",
    "smartcontract": "eth",
    "gas": "eth",
    "finney": "eth",
    "buterin": "eth",
    "dapps": "eth",
    "etherium": "eth",
    "ethers": "eth",
    "ethos": "eth",
    "ethereum2": "eth",
    "eth2": "eth",
    "stallarcoin": "eth",
    "litecoin": "ltc",
    "ltc": "ltc",
    "lite": "ltc",
    "lee": "ltc",
    "silvertobitcoin": "ltc",
    "charlielee": "ltc",
    "litecash": "ltc",
    "gold": "xau",
    "xau": "xau",
    "au": "xau",
    "bullion": "xau",
    "troy": "xau",
    "troyounce": "xau",
    "ouncegold": "xau",
    "preciousmetal": "xau",
    "aurum": "xau",
    "yellowmetal": "xau",
    "goldbar": "xau",
    "goldbullion": "xau",
    "comex": "xau",
    "ingot": "xau",
    "bouillon": "xau",
    "24k": "xau",
    "22k": "xau",
    "18k": "xau",
    "14k": "xau",
    "karat": "xau",
    "silver": "xag",
    "xag": "xag",
    "ag": "xag",
    "ouncesilver": "xag",
    "troyouncesilver": "xag",
    "argentum": "xag",
    "whitemetal": "xag",
    "sterlingsilver": "xag",
    "999fine": "xag",
    "finesilver": "xag",
    "poormansgold": "xag",
    "silverbar": "xag",
    "silverbullion": "xag",
    "peso": "mxn",
    "pesos": "mxn",
    "mxn": "mxn",
    "mexican": "mxn",
    "mexico": "mxn",
    "mx$": "mxn",
    "mexicandollar": "mxn",
    "méjico": "mxn",
    "méxico": "mxn",
    "moneda": "mxn",
    "aztec": "mxn",
    "mayan": "mxn",
    "mexdollar": "mxn",
    "mexicocity": "mxn",
    "cdmx": "mxn",
    "mexicano": "mxn",
    "tijuana": "mxn",
    "nuevopeso": "mxn",
    "brazilian": "brl",
    "brazil": "brl",
    "brl": "brl",
    "real": "brl",
    "reais": "brl",
    "r$": "brl",
    "brasil": "brl",
    "brasilia": "brl",
    "rio": "brl",
    "saopaulo": "brl",
    "amazonia": "brl",
    "amazon": "brl",
    "carioca": "brl",
    "paulista": "brl",
    "centavo": "brl",
    "réis": "brl",
    "rand": "zar",
    "zar": "zar",
    "southafrican": "zar",
    "sa": "zar",
    "southafrica": "zar",
    "sarand": "zar",
    "saffa": "zar",
    "saffer": "zar",
    "mzansi": "zar",
    "azania": "zar",
    "rsa": "zar",
    "pretoria": "zar",
    "johannesburg": "zar",
    "capetown": "zar",
    "durban": "zar",
    "afrikaans": "zar",
    "mandela": "zar",
    "swedish": "sek",
    "sweden": "sek",
    "sek": "sek",
    "kronor": "sek",
    "krona": "sek",
    "sverige": "sek",
    "swedishkrona": "sek",
    "swedishcrown": "sek",
    "stockholm": "sek",
    "gothenburg": "sek",
    "riksbank": "sek",
    "scandinavian": "sek",
    "nordic": "sek",
    "kr": "sek",
    "öre": "sek",
    "svenska": "sek",
    "nok": "nok",
    "norwegian": "nok",
    "norway": "nok",
    "krone": "nok",
    "kroner": "nok",
    "norge": "nok",
    "norwegiancrown": "nok",
    "oslo": "nok",
    "bergen": "nok",
    "trondheim": "nok",
    "norske": "nok",
    "fjord": "nok",
    "viking": "nok",
    "øre": "nok",
    "dkk": "dkk",
    "danish": "dkk",
    "denmark": "dkk",
    "dansk": "dkk",
    "danmark": "dkk",
    "danishkrone": "dkk",
    "danishcrown": "dkk",
    "copenhagen": "dkk",
    "århus": "dkk",
    "aarhus": "dkk",
    "baht": "thb",
    "thb": "thb",
    "thai": "thb",
    "thailand": "thb",
    "siam": "thb",
    "siamese": "thb",
    "thaibaht": "thb",
    "bt": "thb",
    "฿": "thb",
    "บาท": "thb",
    "bangkok": "thb",
    "pattaya": "thb",
    "phuket": "thb",
    "satang": "thb",
    "dirham": "aed",
    "dirhams": "aed",
    "aed": "aed",
    "emirati": "aed",
    "uae": "aed",
    "dubai": "aed",
    "emirates": "aed",
    "unitedarabemirates": "aed",
    "abudhabi": "aed",
    "sharjah": "aed",
    "دبي": "aed",
    "الإمارات": "aed",
    "arabee": "aed",
    "fils": "aed",
    "درهم": "aed",
    "gulfstate": "aed",
    "desertdollar": "aed",
    "hkd": "hkd",
    "hongkong": "hkd",
    "hk$": "hkd",
    "hk": "hkd",
    "香港": "hkd",
    "港元": "hkd",
    "hongkongdollar": "hkd",
    "kowloon": "hkd",
    "lantau": "hkd",
    "victoria": "hkd",
    "sarhk": "hkd",
    "specialadministrativeregion": "hkd",
    "sgd": "sgd",
    "singapore": "sgd",
    "sing": "sgd",
    "sg$": "sgd",
    "s$": "sgd",
    "싱가포르": "sgd",
    "新加坡": "sgd",
    "सिंगापुर": "sgd",
    "singdollar": "sgd",
    "lioncity": "sgd",
    "sentosa": "sgd",
    "changi": "sgd",
    "raffles": "sgd",
    "merlion": "sgd",
    "lkysean": "sgd",
    "zloty": "pln",
    "zlotys": "pln",
    "pln": "pln",
    "polish": "pln",
    "poland": "pln",
    "polska": "pln",
    "zł": "pln",
    "złoty": "pln",
    "warsaw": "pln",
    "warszawa": "pln",
    "krakow": "pln",
    "cracow": "pln",
    "gdansk": "pln",
    "wroclaw": "pln",
    "grosz": "pln",
    "groszy": "pln",
    "forint": "huf",
    "forints": "huf",
    "huf": "huf",
    "hungarian": "huf",
    "hungary": "huf",
    "magyar": "huf",
    "ft": "huf",
    "magyarforint": "huf",
    "budapest": "huf",
    "magyarország": "huf",
    "filler": "huf",
    "fillér": "huf",
    "fillért": "huf",
    "newzealand": "nzd",
    "nzd": "nzd",
    "kiwi": "nzd",
    "nz$": "nzd",
    "kiwidollar": "nzd",
    "nz": "nzd",
    "aotearoa": "nzd",
    "wellington": "nzd",
    "auckland": "nzd",
    "christchurch": "nzd",
    "queencity": "nzd",
    "kea": "nzd",
    "maori": "nzd",
    "shekel": "ils",
    "shekels": "ils",
    "ils": "ils",
    "israeli": "ils",
    "israel": "ils",
    "nis": "ils",
    "newisraelishekel": "ils",
    "₪": "ils",
    "sheqel": "ils",
    "שקל": "ils",
    "שקלים": "ils",
    "agora": "ils",
    "agorot": "ils",
    "jerusalem": "ils",
    "telaviv": "ils",
    "haifa": "ils",
    "holyland": "ils",
    "zion": "ils",
    "hebrew": "ils",
    "ringgit": "myr",
    "myr": "myr",
    "malaysian": "myr",
    "malaysia": "myr",
    "rm": "myr",
    "malaya": "myr",
    "malay": "myr",
    "malayan": "myr",
    "RM": "myr",
    "kualalumpur": "myr",
    "kl": "myr",
    "penang": "myr",
    "sen": "myr",
    "马来西亚": "myr",
    "riyal": "sar",
    "riyals": "sar",
    "sar": "sar",
    "saudi": "sar",
    "saudiarabia": "sar",
    "sr": "sar",
    "ksa": "sar",
    "سعودي": "sar",
    "ريال": "sar",
    "riyalsaudí": "sar",
    "mecca": "sar",
    "makkah": "sar",
    "madinah": "sar",
    "medina": "sar",
    "jeddah": "sar",
    "riyadh": "sar",
    "saudiriyal": "sar",
    "halala": "sar",
    "halalas": "sar",
    "lira": "try",
    "liras": "try",
    "try": "try",
    "turkish": "try",
    "turkey": "try",
    "turkiye": "try",
    "türkiye": "try",
    "türk": "try",
    "tl": "try",
    "ytl": "try",
    "yeni": "try",
    "₺": "try",
    "istanbul": "try",
    "ankara": "try",
    "izmir": "try",
    "antalya": "try",
    "kurus": "try",
    "kuruş": "try",
    "ottoman": "try",
    "rupiah": "idr",
    "idr": "idr",
    "indonesian": "idr",
    "indonesia": "idr",
    "rp": "idr",
    "perak": "idr",
    "jakarta": "idr",
    "surabaya": "idr",
    "bali": "idr",
    "java": "idr",
    "sumatra": "idr",
    "senidonesia": "idr",
    "indo": "idr",
    "nusantara": "idr",
    "php": "php",
    "philippine": "php",
    "philippines": "php",
    "piso": "php",
    "filipino": "php",
    "pinoy": "php",
    "pinay": "php",
    "pilipinas": "php",
    "manila": "php",
    "cebu": "php",
    "davao": "php",
    "sentimo": "php",
    "sentimos": "php",
    "pesofilipino": "php",
    "philippino": "php",
    "pakistani": "pkr",
    "pakistan": "pkr",
    "pkr": "pkr",
    "pak": "pkr",
    "rupeepakistani": "pkr",
    "پاکستانی روپیہ": "pkr",
    "روپیہ": "pkr",
    "rspk": "pkr",
    "karachi": "pkr",
    "lahore": "pkr",
    "islamabad": "pkr",
    "rawalpindi": "pkr",
    "dong": "vnd",
    "vnd": "vnd",
    "vietnamese": "vnd",
    "vietnam": "vnd",
    "viet": "vnd",
    "đồng": "vnd",
    "đ": "vnd",
    "việtnam": "vnd",
    "hanoi": "vnd",
    "hànội": "vnd",
    "hochiminh": "vnd",
    "hồchíminh": "vnd",
    "saigon": "vnd",
    "sàigòn": "vnd",
    "xu": "vnd",
    "twd": "twd",
    "taiwanese": "twd",
    "taiwan": "twd",
    "nt$": "twd",
    "newtaiwandollar": "twd",
    "formosa": "twd",
    "台灣": "twd",
    "台湾": "twd",
    "臺灣": "twd",
    "台币": "twd",
    "台幣": "twd",
    "台元": "twd",
    "新台幣": "twd",
    "新台币": "twd",
    "taipei": "twd",
    "taichung": "twd",
    "kaohsiung": "twd",
    "czk": "czk",
    "czech": "czk",
    "czechrepublic": "czk",
    "koruna": "czk",
    "koruny": "czk",
    "czechia": "czk",
    "kč": "czk",
    "ceska": "czk",
    "česká": "czk",
    "prague": "czk",
    "praha": "czk",
    "brno": "czk",
    "ostrava": "czk",
    "haler": "czk",
    "haléř": "czk",
    "česko": "czk",
    "chilean": "clp",
    "chile": "clp",
    "clp": "clp",
    "pesochileno": "clp",
    "santiaguino": "clp",
    "chilenos": "clp",
    "santiago": "clp",
    "valparaiso": "clp",
    "cl$": "clp",
    "centavoclp": "clp",
    "andean": "clp",
    "argentinian": "ars",
    "argentina": "ars",
    "ars": "ars",
    "arg$": "ars",
    "argentino": "ars",
    "argentinos": "ars",
    "pesoargentino": "ars",
    "buenosaires": "ars",
    "porteño": "ars",
    "porteno": "ars",
    "bsas": "ars",
    "mendoza": "ars",
    "cordoba": "ars",
    "centavoars": "ars",
    "xrp": "xrp",
    "ripple": "xrp",
    "ripples": "xrp",
    "xrptoken": "xrp",
    "xrpcoin": "xrp",
    "rpl": "xrp",
    "ripplecoin": "xrp",
    "globalcoin": "xrp",
    "bankcoin": "xrp",
    "kenyan": "kes",
    "kenya": "kes",
    "kes": "kes",
    "kenyanshilling": "kes",
    "ksh": "kes",
    "ke": "kes",
    "nairobi": "kes",
    "mombasa": "kes",
    "jamhuri": "kes",
    "nyayo": "kes",
    "centkes": "kes",
    "shilingi": "kes",
    "senti": "kes",
    "naira": "ngn",
    "ngn": "ngn",
    "nigerian": "ngn",
    "nigeria": "ngn",
    "ng": "ngn",
    "9ja": "ngn",
    "naijan": "ngn",
    "₦": "ngn",
    "lagos": "ngn",
    "abuja": "ngn",
    "kobo": "ngn",
    "egyptian": "egp",
    "egypt": "egp",
    "egp": "egp",
    "egyptianpound": "egp",
    "eg": "egp",
    "egyp": "egp",
    "جنيه": "egp",
    "مصر": "egp",
    "le": "egp",
    "ep": "egp",
    "cairo": "egp",
    "alexandria": "egp",
    "giza": "egp",
    "piastre": "egp",
    "qirsh": "egp",
    "قرش": "egp",
    "taka": "bdt",
    "bdt": "bdt",
    "bangladeshi": "bdt",
    "bangladesh": "bdt",
    "bangla": "bdt",
    "টাকা": "bdt",
    "tk": "bdt",
    "৳": "bdt",
    "dhaka": "bdt",
    "chittagong": "bdt",
    "বাংলা": "bdt",
    "poisha": "bdt",
    "paisabdt": "bdt",
    "পয়সা": "bdt",
    "romanian": "ron",
    "romania": "ron",
    "ron": "ron",
    "leu": "ron",
    "lei": "ron",
    "ro": "ron",
    "română": "ron",
    "românesc": "ron",
    "bucharest": "ron",
    "bucurești": "ron",
    "bucuresti": "ron",
    "bani": "ron",
    "ban": "ron",
    "hryvnia": "uah",
    "uah": "uah",
    "ukraine": "uah",
    "ukrainian": "uah",
    "ukr": "uah",
    "гривня": "uah",
    "₴": "uah",
    "грн": "uah",
    "kyiv": "uah",
    "київ": "uah",
    "україна": "uah",
    "kopiyka": "uah",
    "копійка": "uah",
    "xlm": "xlm",
    "lumens": "xlm",
    "stellar": "xlm",
    "stellarlumens": "xlm",
    "link": "link",
    "chainlink": "link",
    "linktoken": "link",
    "yfi": "yfi",
    "yearnfinance": "yfi",
    "yearn": "yfi"
}